[
    {   "name":"CristianoRonaldo", "club":"RealMadrid", "country":"Portugal"  },
    {   "name":"LionelMessi", "club":"Barcelona", "country":"Argentina"  },
    {   "name":"AntoineGriezmann", "club":"AthleticoMadrid", "country":"France"  },
    {   "name":"NeymarJr", "club":"PSG", "country":"Brazil"  },
    {   "name":"HarryKane", "club":"TottenhamHotspur", "country":"England"  },
    {   "name":"Marcelo", "club":"RealMadrid", "country":"Brazil"  },
    {   "name":"PauloDybala", "club":"Juventus", "country":"Argentina"  },
    {   "name":"ZlatanIbrahimovic", "club":"ManchesterUnited", "country":"Sweden"  },
    {   "name":"SunilChhetri", "club":"BengaluruFC", "country":"India"  }
]